streamlit_slb_card/__init__.py
streamlit_slb_card/example.py
streamlit_slb_card/frontend/build/asset-manifest.json
streamlit_slb_card/frontend/build/bootstrap.min.css
streamlit_slb_card/frontend/build/index.html
streamlit_slb_card/frontend/build/static/js/main.305b8d4f.js
streamlit_slb_card/frontend/build/static/js/main.305b8d4f.js.LICENSE.txt
streamlit_slb_card/frontend/build/static/js/main.305b8d4f.js.map
streamlit_slb_card-1.0.8.dist-info/LICENSE
streamlit_slb_card-1.0.8.dist-info/METADATA
streamlit_slb_card-1.0.8.dist-info/WHEEL
streamlit_slb_card-1.0.8.dist-info/top_level.txt
streamlit_slb_card-1.0.8.dist-info/RECORD
